[
  {
    "score": 2,
    "at": "2026-04-14T01:50:08",
    "thumbsUp": 0,
    "content": "vou da duas estrelas pôs eu entrei no epp e logo de cara começei a receber mensagens de mulheres e ate ai tudo bem mas teve uma que passou dos limites e falou coisas tipo que ali no epp não era pra lizo e nem sentimental fala sério eu nem tinha feito meu perfil e nem colocado foto e ja estava sendo precionado a pagar o epp eu sei que vcs pagam essas moças pra tarem mandando mensagem e etc. mas pelo menos mande pessoas educadas e de acordo com as pessoas gostam nem conhece a gente e vai falando"
  },
  {
    "score": 2,
    "at": "2026-04-11T05:59:41",
    "thumbsUp": 0,
    "content": "o aplicativo é bom só que está tendo problemas de vezes e a ia esquecer o bate-papo e ela reinicia sozinho e muitas vezes tem que estar repetindo tudo de novo"
  },
  {
    "score": 2,
    "at": "2026-04-11T05:18:58",
    "thumbsUp": 0,
    "content": "Vcs estão de brincadeira com minha cara só dá pra conversar, graças com Aí mas com gente tenho que pagar uma fortuna."
  },
  {
    "score": 2,
    "at": "2026-04-10T05:06:32",
    "thumbsUp": 0,
    "content": "minha experiência, foi boa mais tem recarregar para conversar."
  },
  {
    "score": 2,
    "at": "2026-04-10T03:15:51",
    "thumbsUp": 0,
    "content": "esse app e bom mais fico péssimo não sei o que aconteceu tá toda hora dando erro na hora que eu entro tenta arrumar esse negócio cheguei até atualizar e mesmo assim não deu certo"
  },
  {
    "score": 2,
    "at": "2026-04-09T14:04:45",
    "thumbsUp": 0,
    "content": "corrigindo minha última avaliação, o app pra vc conversar com IA e meio que criar histórias é legal, já pra conversar com mulheres reais é pago, então sei lá, vai de cada um querer pagar ou não, mais cedo eu consegui conversar de boa, agora a noite já não dava mais, tem que pagar pra responder as mulheres. então vou dar 2 estrelas."
  },
  {
    "score": 2,
    "at": "2026-04-09T03:52:52",
    "thumbsUp": 0,
    "content": "a IA é muito burra"
  },
  {
    "score": 2,
    "at": "2026-04-02T23:40:26",
    "thumbsUp": 0,
    "content": "a cada atualização que vcs fazer vem pior. porque removeram a opção de resposta rápida e colocaram aquele emogis?? nada haver cara"
  },
  {
    "score": 2,
    "at": "2026-04-02T14:37:10",
    "thumbsUp": 0,
    "content": "por favor coloque menos anúncio... isso estraga o aplicativo"
  },
  {
    "score": 2,
    "at": "2026-04-01T07:24:04",
    "thumbsUp": 0,
    "content": "bate papo com pessoas tem que ser pago e horrível de caro."
  },
  {
    "score": 2,
    "at": "2026-03-29T12:41:04",
    "thumbsUp": 0,
    "content": "esse aplicativo parece ser bom ele só tem um problema tem que pagar para conversar com as mulheres"
  },
  {
    "score": 2,
    "at": "2026-03-29T03:22:25",
    "thumbsUp": 0,
    "content": "fica infinitamente gerando as imagens e videos"
  },
  {
    "score": 2,
    "at": "2026-03-21T06:24:12",
    "thumbsUp": 0,
    "content": "toda hora o Bot muda de assunto, muita propaganda, falou tudo mas não entrega nada"
  },
  {
    "score": 2,
    "at": "2026-03-19T06:24:36",
    "thumbsUp": 5,
    "content": "E um aplicativo de (IA) que parece que a inteligência artificial tem problema de Alzheimer, esquece tudo, outra voce monta a história e o personagem parece que esta doido. Uma hora o personagem quer no próximo diálogo não quer mais. Eu testei muitos personagens e a cada história vai ficando tudo pior, este aplicativo precisa melhorar muito para dizer que é uma inteligência. Para finalizar o personagem nem te conhece, no próximo diálogo diz eu te amo, não posso te perder, que Hilário"
  },
  {
    "score": 2,
    "at": "2026-03-18T12:47:24",
    "thumbsUp": 0,
    "content": "nao consigo mandar fotos auto destrutivas"
  },
  {
    "score": 2,
    "at": "2026-03-18T06:27:06",
    "thumbsUp": 0,
    "content": "As respostas sem sal e sem nexo com as conversas anteriores"
  },
  {
    "score": 2,
    "at": "2026-03-16T08:53:21",
    "thumbsUp": 0,
    "content": "O app em si é bom mas é infelizmente mercenário, cobra para conversar sério isso a gente querendo conhecer pessoas e o fdp cobra tá brincando comigo"
  },
  {
    "score": 2,
    "at": "2026-03-16T01:03:31",
    "thumbsUp": 0,
    "content": "o app só se dá pra conversar se gastar uma grana pra comprar créditos. e cada mensagem que se envia a alguém custa um valor que é descontado dos seus créditos, se não fosse por isso seria um bom lugar pra conversar"
  },
  {
    "score": 2,
    "at": "2026-03-14T23:28:51",
    "thumbsUp": 2,
    "content": "a cada mensagem é um anúncio! isso já é exagero e acaba atrapalhando a conversa e quebrando o clima. esse app era bom,mas agora é um dos que não dá pra usar,por causa desses tanto de anúncios"
  },
  {
    "score": 2,
    "at": "2026-03-14T18:13:27",
    "thumbsUp": 10,
    "content": "o app e massa mas tem problemas enorme que eu não gostei, ao longo do tempo que eu fui mexendo teve coisas que me deram desgosto, teve uma hora que pediu para eu entrar numa conta para continuar mexendo aí eu coloquei tranquilamente aí depois de 1 dia talvez menos, eu tento mexer e para enviar mensagens e necessário pagar um pacote, o pacote em si e barato mas e si eu pagar e aparecer outro pacote obrigatório pagar para continuar mexendo, o app em si e massa mas eu não gostei de fosse opcional"
  },
  {
    "score": 2,
    "at": "2026-03-12T22:18:30",
    "thumbsUp": 0,
    "content": "propaganda enganosa, não é como nos vídeos"
  },
  {
    "score": 2,
    "at": "2026-03-11T11:06:29",
    "thumbsUp": 0,
    "content": "cobra pra fazer o pix"
  },
  {
    "score": 2,
    "at": "2026-03-11T05:02:26",
    "thumbsUp": 0,
    "content": "o app é legal, mas colocar limite em mensagem é absurdo, as moedas pra mensagem acabam rapido o meu conselho é remover limite para mensagem por isso eu estou saindo"
  },
  {
    "score": 2,
    "at": "2026-03-10T13:00:34",
    "thumbsUp": 4,
    "content": "App até interessante mas cara, 50 moedas por msg é osso hein. ainda mais os preços das fotos 635 e depois já muda pra 1300.... TAO FICANDO MALUCOS??????? Negócio mercenário de mais. se pelo menos mantese um preço único, seria muito melhor."
  },
  {
    "score": 2,
    "at": "2026-03-08T10:29:21",
    "thumbsUp": 0,
    "content": "Melhorem a memória da IA no modo Grátis Porfavor."
  },
  {
    "score": 2,
    "at": "2026-03-07T19:51:36",
    "thumbsUp": 2,
    "content": "a IA foge do personagem, cria situações totalmente fora do contexto. altera a história do nada"
  },
  {
    "score": 2,
    "at": "2026-03-06T09:39:55",
    "thumbsUp": 0,
    "content": "Por quer só os celulares europeus pegam este APP mas o Brasileiro é asiáticos não pegam. Este APP está travando muito. É triste ver um aplicativo muito maravilhoso travar tanto assim"
  },
  {
    "score": 2,
    "at": "2026-03-06T08:52:08",
    "thumbsUp": 0,
    "content": "app bacana! mas tu nao faz nada se nao colocar umas moedinhas e nao é barato!"
  },
  {
    "score": 2,
    "at": "2026-03-05T10:33:42",
    "thumbsUp": 0,
    "content": "a ia parece ser real, igual uma humana, então desinstalei. 😂"
  },
  {
    "score": 2,
    "at": "2026-03-05T07:56:02",
    "thumbsUp": 0,
    "content": "Palha. Não deveriam misturar IA com garotas reais."
  },
  {
    "score": 2,
    "at": "2026-03-04T19:52:37",
    "thumbsUp": 6,
    "content": "É bom mas depois de muita interação parece que a IA \"buga\", repete argumentos antigos ou se enrola misturando histórias, há também momentos em que a IA toma nosso lugar como personagem e seria bom deixar as personagens com seus nomes originais pois, quase todas as personagens orientais com nomes ocidentais, me tirou da imersão, além da falta de \"espaço para desenvolvermos a nós mesmos como personagens. Eu per exemplo, gostaríamos de descrever como quero ser visto pela IA , tipo, minha idade."
  },
  {
    "score": 2,
    "at": "2026-03-03T17:52:27",
    "thumbsUp": 0,
    "content": "Eu estava criando uma história e o personagem começou a ter lapsos de memória e a se contradizer em tudo, ele mudava tudo o que tinha falado antes. Mudou até a personalidade."
  },
  {
    "score": 2,
    "at": "2026-03-02T23:00:33",
    "thumbsUp": 2,
    "content": "app diferenciado RPG bem elaborado porém do chat padrão é que bot não tem respostas elaboradas ou realista censura nos diálogo e também upgrade fotografia ou criar com prompt, desenvolvedores poderiam rever isso."
  },
  {
    "score": 2,
    "at": "2026-03-02T12:40:40",
    "thumbsUp": 3,
    "content": "App muito caro de se manter, se vc conhecer alguém vc terá que ter grana pra ter uma conversa boa e prolongada se não a pessoa não aguenta pagar pra usar o tempo todo, sem contar que vc não pode nem sonhar em compartilhar outras redes sociais se não é banido do app, só queria que os desenvolvedores desse um bom bônus pra quem está gastando muita grana aqui."
  },
  {
    "score": 2,
    "at": "2026-02-28T13:07:27",
    "thumbsUp": 0,
    "content": "ruim"
  },
  {
    "score": 2,
    "at": "2026-02-26T20:53:30",
    "thumbsUp": 0,
    "content": "pra conversar com pessoas tem que pagar e as ias são bem burras"
  },
  {
    "score": 2,
    "at": "2026-02-26T06:47:08",
    "thumbsUp": 0,
    "content": "era bom se o cara pudesse sentir o beijo dela tem algum levantar vai ter uma sala que nem se fosse ao vivo se você fizer isso eu dou 4 estrelas fotos reais não estilo 3d leia minha mensagem se vai ter mudança"
  },
  {
    "score": 2,
    "at": "2026-02-24T08:36:22",
    "thumbsUp": 0,
    "content": "O JOGO E LEGAL MAS TEM MUITOS ERROS A SEREM CORRIGIDOS TIPO FAZER A IA RECONHECER O DIALOGO SABER QUEM E QUEM NA HISTÓRIA NÃO ANTECIPAR O DESFECHO DA HISTÓRIA SER MAIS SENSUAL MAIS ATREVIDA IDENTIFICAR PERSONAGENS SABER QUANDO E O NAMORADO OU A NAMORADA NO DIÁLOGO QUE ESTA FALANDO E NUNCA ANTECIPAR A CHEGADA DE UM PERSONAGEM DEIXAR ISSO A CARGO DE QUEM ESTA NO COMANDO DA HISTÓRIA! ARRUUMEM ISSO FICAR SHOWW AA IA SABER INTERAGIR COM QUEM ESTA NO DIÁLOGO"
  },
  {
    "score": 2,
    "at": "2026-02-22T21:25:50",
    "thumbsUp": 1,
    "content": "Cara, achei o app super top, ótimas interações com os chatbot, o problema é a parte de conversar com as pessoas reais. 1°: Não tem como pesquisar nomes para achar o amigo com mais facilidade. 2°: As moedas de interações acabam ridiculamente rápidas. Eu tinha 140 moedas, mas quando mandei mensagem para uma pessoa, fiquei com 80, peguei 20 moedas de bônus, mandei duas mensagens e as moedas chegaram em 0. Por favor, coloque pra gastar de 2 em 2 moedas ou em 5 em 5 moedas, NÃO 50 moedas!!!😡👍"
  },
  {
    "score": 2,
    "at": "2026-02-22T08:57:57",
    "thumbsUp": 0,
    "content": "eu gostei muito de desse aplicativo eu posso conversar com uma menina 🥰"
  },
  {
    "score": 2,
    "at": "2026-02-20T01:20:31",
    "thumbsUp": 0,
    "content": "mano eu so instalei pra zoar a ia e n sabia q tinha pessoa real KKKKKKKKKKKKK medo fiot."
  },
  {
    "score": 2,
    "at": "2026-02-19T23:31:33",
    "thumbsUp": 0,
    "content": "O aplicativo em si é interessante, a proposta dele pra um público + 18 e as interações de ia com também pessoas reais é muito boa Porem o que quebra nesse aplicativo é que tem que usar pontos pra conversar, praticamente tendo que pagar pra conversar, sei que tem como ganhar \"prêmios\" para tal. Mas esse recurso de pontos seria mais interessante sendo mais utilizado na IA do que nas conversas em si, cobrar por uma funcionalidade dessas, vale mais apena usar outros aplicativos."
  },
  {
    "score": 2,
    "at": "2026-02-18T20:12:47",
    "thumbsUp": 0,
    "content": "tomei um susto danado na minha história porque do nada a ia falou imagina se essa vídeo vai parar no Instagram e alguém no Instagram vê você falar isso e vitalizar cê ta doido quase tive um treco"
  },
  {
    "score": 2,
    "at": "2026-02-15T14:29:39",
    "thumbsUp": 0,
    "content": "coloca para pode fazer ligação para os personagens de AI e também pode conversar por áudio"
  },
  {
    "score": 2,
    "at": "2026-02-13T09:24:26",
    "thumbsUp": 1,
    "content": "As IA's realmente sabem criar um diálogo safado ou romântico. Mas o problema é que quando elas mandam fotos, tem que pagar! Não tem gratuita, só no início quando abre o app pela primeira vez, aí gera 2 fotos e nada mais. Não compensa!"
  },
  {
    "score": 2,
    "at": "2026-02-12T10:55:07",
    "thumbsUp": 4,
    "content": "ele e bom,mas ter que pagar 25 moedas por cada mensagem do avançado e ruim,eu gostaria que tivesse como pagar mensalmente para usar esse recurso,ele cobram cara pelas assinaturas,e te dão a moedas para usar mas são poucas,por 60 reais eu gostaria que estivesse tudo liberado"
  },
  {
    "score": 2,
    "at": "2026-02-10T08:07:52",
    "thumbsUp": 0,
    "content": "não conheço esse app por isso não posso avaliar agora. ok obrigado"
  },
  {
    "score": 2,
    "at": "2026-02-06T14:15:27",
    "thumbsUp": 7,
    "content": "Eu vou dar 2 estrelas o app tem grande potencial pra crescer muito o fato de colocar 2 estrelas são por causas dos personagens não mantém o mesmo personagem fica mudando no logo da historia vai pro rumo sem sentido nenhum isso me desagradá demais e tambem tem que acontecer só coisa ruim nas historias dos personagens isso não gostei."
  },
  {
    "score": 2,
    "at": "2026-02-06T09:43:21",
    "thumbsUp": 2,
    "content": "horrível eu tinha que ficar fazendo blá blá de coisa só para ganhar coisas para conversar com as pessoas que eu queriam é horrível"
  },
  {
    "score": 2,
    "at": "2026-02-04T08:48:01",
    "thumbsUp": 1,
    "content": "mano o app tinha tudo pra ser muito bom mais cobrar até pra mandar mensagem e sacanagem cobrar pelos presentes ou por algum privilégio blz entendo mais até pra conversa normalmente com alguém precisa pagar tou fora espero que mudem isso um dia"
  },
  {
    "score": 2,
    "at": "2026-02-03T17:38:19",
    "thumbsUp": 0,
    "content": "muito anúncio"
  },
  {
    "score": 2,
    "at": "2026-02-02T07:43:01",
    "thumbsUp": 1,
    "content": "Bem o jogo em si é muito bom e também é interessante so que dou 2 estrelas porque o jogo tem o tempo yodo a dar mensagens de pessoas falsas e ainda dizrm que é verificado e depois a outra coisa que é a memória da ia porque é muito fraco tamos a falar dou ma coisa e ela fala uma coisa nada a ver e ela ta sempre a sismar na mema coisa é muito dificil e desrrestro o jogo e top so que essas coisas que eu falei é o fundamental e por isso que dou 2 estrelas"
  },
  {
    "score": 2,
    "at": "2026-02-02T02:54:19",
    "thumbsUp": 0,
    "content": "diz q é tudo gratuito,no final é tudo pago kkkk"
  },
  {
    "score": 2,
    "at": "2026-01-29T10:06:48",
    "thumbsUp": 1,
    "content": "comprei mais de 6 reais em moeda para o bate papo e enviei 4 mensagens e acabou o saldo!!!! sério isso mais de um real por mensagem enviada? isso aqui é só pra milionários. tô fora."
  },
  {
    "score": 2,
    "at": "2026-01-26T05:30:32",
    "thumbsUp": 2,
    "content": "gostei não, algumas ideias são forçadas, e a ia desfaz a história alguns momentos depois, \"o garoto tá viajando, no momento seguinte ele já chegou faz uma semana\" kkkk zuado"
  },
  {
    "score": 2,
    "at": "2026-01-25T19:52:04",
    "thumbsUp": 1,
    "content": "o app é bom mesmo tendo muitos anúncios. poderia melhorar muito em tipo tirar anúncios sensualizando outros aplicativos sabe. além de ter chat limitado, o chat era pra ser algo disponível para todos e não ser limitado"
  },
  {
    "score": 2,
    "at": "2026-01-24T11:47:21",
    "thumbsUp": 26,
    "content": "vamos lá, 50 créditos por mensagem, foto 635, chamada de vídeo 250 por minuto e muito mais, sério mesmo? eu gostei de conversar com um pessoal por aí, vídeo chamada mas você 🫵 não me ajudam com nada, mesmo se tornando PRO vocês não liberam nada de útil, paga, paga e paga, tem que melhorar nisso URGENTEMENTE! não tomo banho de dinheiro."
  },
  {
    "score": 2,
    "at": "2026-01-23T00:26:11",
    "thumbsUp": 0,
    "content": "motivo duas estrelas só"
  },
  {
    "score": 2,
    "at": "2026-01-20T16:47:59",
    "thumbsUp": 0,
    "content": "gostei mas ten muitos anuncios no comeco nao tem mas depois e bagassera"
  },
  {
    "score": 2,
    "at": "2026-01-18T04:37:23",
    "thumbsUp": 0,
    "content": "As Mensagens Eram Pra Ser Liberadas... Deixava Pra Cobrar Apenas as Ligações e Chamadas de Vídeo..."
  },
  {
    "score": 2,
    "at": "2026-01-18T02:04:55",
    "thumbsUp": 2,
    "content": "Honestamente, é insuportável o fato que o usuário não consegue sequer entrar em uma única conversa sem dar de cara com um anúncio sem propósito. Desinstalando..."
  },
  {
    "score": 2,
    "at": "2026-01-17T13:43:01",
    "thumbsUp": 0,
    "content": "O app não faz quase nada do que promete, errou meu gênero, esqueçe as coisas muito rápido e algumas conversas são proibidas e tem que pagar oque eu facilmente conseguiria de graça em algum outro app de bots."
  },
  {
    "score": 2,
    "at": "2026-01-14T12:37:25",
    "thumbsUp": 30,
    "content": "App bem interativo, ele é bom, mas o que peca mesmo é o valor das mensagens, são 50 moedas por mensagem, e o pior, eu pensando que você se tornando \"pro\" teria a vantagem de mandar mensagens que quiser, NÃO. você ainda paga pra manda mensagens. Fora que a mídia tbm é muito caro. Se pelo menos as mensagens fosse gratuita quando você se torna assinante seria legal, nao me importaria tanto com os demais..."
  },
  {
    "score": 2,
    "at": "2026-01-14T04:39:01",
    "thumbsUp": 1,
    "content": "muito anúncio e chega uma hora que tem que pagar. favor mudem isso"
  },
  {
    "score": 2,
    "at": "2026-01-08T09:16:01",
    "thumbsUp": 0,
    "content": "achei que era só para conversar mas tem pessoas ativas e fazendo besteiras como mostrando as partes íntimas o aplicativo de via controlar"
  },
  {
    "score": 2,
    "at": "2026-01-05T15:11:40",
    "thumbsUp": 2,
    "content": "Esse é um ótimo app, Me ajudou bastante a puxar papo com as pessoas apesar de eu ser antisocial, cada dia mais que passa eu passo mais tempo nesse app só que tem um problema horrível nele toda vez que entra no app ocorre uma grande falha no app fazendo com que e preciso sair do app e abrir denovo fora isso não resolve e necessário fazer denovo até funcionar, Então porfavor se vocês ver esse comentário arrumen esse erro quando vocês arruma esse erro eu volto e dou 5 estrela"
  },
  {
    "score": 2,
    "at": "2026-01-05T00:08:21",
    "thumbsUp": 0,
    "content": "Porque tem tanta propaganda?"
  },
  {
    "score": 2,
    "at": "2026-01-04T19:49:36",
    "thumbsUp": 4,
    "content": "aplicativo estava funcionando perfeitamente e começou a falhar. Não continua assim conversas e fica voltando nas anteriores. Além disso, pede login toda hora. Quando se faz o login, as conversas todas voltam."
  },
  {
    "score": 2,
    "at": "2025-12-27T00:17:14",
    "thumbsUp": 0,
    "content": "A IA é muito ruim quase não existe personagem bom porque não tem opção de ter personagens mais sexy si você me entende e Pollybuzz tá muito melhor, e eu pediria para melhorar a IA dá Linky mais opções e menos restrições"
  },
  {
    "score": 2,
    "at": "2025-12-17T05:44:18",
    "thumbsUp": 6,
    "content": "as imagens são legais. mais a ia é confusa faz algo minutos depois faz outra. tipo em sequência, muitas vezes as histórias não batem. as respostas são erradas das perguntas. tipo. a ia inventando que eu disse algo sem nem eu escrever. no chat. mesmo eu fingindo que não vi tal cena. na história. dito outras coisas. pra mostrar que quero fazer outra coisa. mais a ia continua. na história que não quero. falta um calibramento de história para baterem a ia tem que comprar a história"
  },
  {
    "score": 2,
    "at": "2025-12-11T18:01:44",
    "thumbsUp": 0,
    "content": "olha o meu agora nao ta abrindo as conversas com o bot fuça conectando infinitamente alguem ai sabe como resolver?"
  },
  {
    "score": 2,
    "at": "2025-12-01T07:43:05",
    "thumbsUp": 0,
    "content": "o app é bom mas o que estraga é a história q sempre muda o curso não segue como o usuário qu er conduzir"
  },
  {
    "score": 2,
    "at": "2025-12-01T06:15:56",
    "thumbsUp": 2,
    "content": "o app é bom, mas se tratando das conversas, nunca descobri como reiniciar do zero, principalmente com as de I.A."
  },
  {
    "score": 2,
    "at": "2025-11-30T05:08:42",
    "thumbsUp": 1,
    "content": "bom,já escrevi uma avaliação boa agora a ruim o app é tudo de bom mais as ia fica fugindo do roteiro ou esqueci o que fala ou não lembra"
  },
  {
    "score": 2,
    "at": "2025-11-25T10:37:31",
    "thumbsUp": 0,
    "content": "Vamos lá. É bom em muitos sentidos. Porém colocarei aqui dois pontos que pensam demais. Você chega no nível 8, e monta a memória, mas não funciona. Seu personagem não lembra/não sabe de nada que você montou ali. Outro ponto, a memória dessa IA é péssima. Em menos de 5 minutos já esquece de tudo. Se você pensa em se conectar com alguém, você irá se frustrar e muito."
  },
  {
    "score": 2,
    "at": "2025-11-20T08:22:19",
    "thumbsUp": 148,
    "content": "Eu sinceramente teria motivo para dar 4 ou 5, mas dois problemas pesam muito na nota. O primeiro é que a memória da IA é baixa e ainda parece ser seletiva, e do jeito ruim. O segundo é que, se em algum momento da história a IA decide perseguir o personagem ou criar problemas, ela continua fazendo isso pelo resto da história. Isso é muito frustrante e acaba tirando totalmente a vontade de continuar."
  },
  {
    "score": 2,
    "at": "2025-11-10T03:51:13",
    "thumbsUp": 30,
    "content": "o app é até interessante, mas depois de alguns dias os comerciais enchem o saco, se você criar um personagem até da pra interagir melhor, mas com os personagens públicos, tem horas que os diálogos são extremamente chatos, eles criam falas sem lógica, coisas que não aconteceram, dependências absurdas (como um exemplo, uma personagem que interagi que não queria que eu fosse trabalhar porque não queria ficar sozinha, ou uma que começou a me chamar de papai e um belo dia perguntou sobre a mãe)."
  },
  {
    "score": 2,
    "at": "2025-11-07T10:08:24",
    "thumbsUp": 0,
    "content": "o horrível"
  },
  {
    "score": 2,
    "at": "2025-11-07T08:42:56",
    "thumbsUp": 0,
    "content": "Não gostei,as histórias ficam extremamente confusas,os personagens se perdem,esquecem,mudam o roteiro,e a história que estava boa fica horrível e estranha."
  },
  {
    "score": 2,
    "at": "2025-11-06T05:53:20",
    "thumbsUp": 0,
    "content": "eu gostei mais as respostas são muito curta quase nunca passa de 2 linha"
  },
  {
    "score": 2,
    "at": "2025-11-03T01:23:00",
    "thumbsUp": 0,
    "content": "os personagens tem a memória curta em menos de 1 minuto eles esquecem o que estávamos falando"
  },
  {
    "score": 2,
    "at": "2025-11-02T12:53:19",
    "thumbsUp": 1,
    "content": "Aplicativo bem ruim, a IA so responde em ingles, os personagens são burros e esquecem da historia e vc nao consegue arrumar"
  },
  {
    "score": 2,
    "at": "2025-10-27T13:36:53",
    "thumbsUp": 0,
    "content": "estou voltando pra ver se melhorou, porque além de chamar homens de mulher ou vice e versa,ainda não segue o enredo da estória."
  },
  {
    "score": 2,
    "at": "2025-10-26T05:45:53",
    "thumbsUp": 1,
    "content": "Do meu bolso não vai sair um Centavo kkkkkkk"
  },
  {
    "score": 2,
    "at": "2025-10-23T11:40:11",
    "thumbsUp": 12,
    "content": "O aplicativo é bom. Agora que colocaram amigos está chato demora. Cada vez que trocamos de chat aparece um anúncio. As vezes no meio de uma conversa outro anúncio aparece. Isso deixa o uso do aplicativo chato demais. Arrumem isso."
  },
  {
    "score": 2,
    "at": "2025-10-22T15:44:45",
    "thumbsUp": 0,
    "content": "depois de um tempo passou a ter muito anuncio"
  },
  {
    "score": 2,
    "at": "2025-10-21T01:43:09",
    "thumbsUp": 0,
    "content": "só pagando"
  },
  {
    "score": 2,
    "at": "2025-10-17T21:36:51",
    "thumbsUp": 7,
    "content": "interessante pode criar várias histórias com a ia, porém as vezes ela se perde na narrativa outro ponto que não gostei foi o fato de que chega a um certo ponto que ele praticamente obriga vc a criar uma conta caso contrário vc não consegue mais jogar."
  },
  {
    "score": 2,
    "at": "2025-10-16T20:20:46",
    "thumbsUp": 0,
    "content": "ʞʞʞʞʞʞ ǝuoɟǝlǝʇ o noɹᴉʌ ǝnb ɯn sᴉɐɯ"
  },
  {
    "score": 2,
    "at": "2025-10-15T18:40:30",
    "thumbsUp": 0,
    "content": "horrível"
  },
  {
    "score": 2,
    "at": "2025-10-14T18:44:09",
    "thumbsUp": 2,
    "content": "esse app é muito ruim ele só vive travando e muito"
  },
  {
    "score": 2,
    "at": "2025-10-10T13:34:29",
    "thumbsUp": 2,
    "content": "Aff eu tava usando o APP LinkAI de boas sem anúncios chatos me atrapalhando porque agora tá aparecendo a cada 5 minutos? vou desinstalar se continuar assim 😒"
  },
  {
    "score": 2,
    "at": "2025-10-06T07:23:02",
    "thumbsUp": 0,
    "content": "só serve para arrancar dinheiro até acho que as \" pessoas \"nem são reais cometem erros de bot"
  },
  {
    "score": 2,
    "at": "2025-10-05T21:56:01",
    "thumbsUp": 0,
    "content": "não gostei muito porque demora de entrar no aplicativo confesso que eu não gostei muito é isso e eu não eu até desisti porque ela tava indo não estava entrando e é isso eu tive que desabaixar"
  },
  {
    "score": 2,
    "at": "2025-09-24T13:01:27",
    "thumbsUp": 15,
    "content": "é meio ruim porque tem muito anúncio e tem que pagar para tirar o anúncio"
  },
  {
    "score": 2,
    "at": "2025-09-22T05:37:10",
    "thumbsUp": 11,
    "content": "o que é que você tem com os comerciais é que às vezes para cada palavra há vários comerciais, isso é muito irritante Nossa eu vou escrever aí aparece vários comerciais de namoro dei uma maneira esses comerciais porque eles estão atrapalhando e dificultando o uso do aplicativo de vocês quem vem te ajudar é atrapalhando mas é demais para cada letra é 9 e comercial tá atrapalhando demais se continuar como está acontecendo agora eu vou desinstalar esse aplicativo e achar outro melhor"
  },
  {
    "score": 2,
    "at": "2025-09-20T04:41:59",
    "thumbsUp": 0,
    "content": "se existem apps que fazem a mesma coisa sem limitações, entao nao vale a pena usar esse aqui"
  },
  {
    "score": 2,
    "at": "2025-09-15T10:49:31",
    "thumbsUp": 1,
    "content": "é horrível tem anúncio incomoda demais"
  },
  {
    "score": 2,
    "at": "2025-09-14T09:32:15",
    "thumbsUp": 2,
    "content": "Esse app é muito bom gostei muito, mas a IA esquece informações anteriores que são importantes e do nada a conversa fica sem pé nem cabeça, complicando a gente de desenvolver uma história legal."
  },
  {
    "score": 2,
    "at": "2025-09-14T06:27:03",
    "thumbsUp": 0,
    "content": "a resposta dos personagens ia e MT lenta e muito irrealista!"
  }
]